dragonfly/__init__.py
dragonfly/__main__.py
dragonfly/_platform_checks.py
dragonfly/config.py
dragonfly/error.py
dragonfly/loader.py
dragonfly/log.py
dragonfly/parser.py
dragonfly/timer.py
dragonfly/accessibility/__init__.py
dragonfly/accessibility/atspi.py
dragonfly/accessibility/base.py
dragonfly/accessibility/controller.py
dragonfly/accessibility/ia2.py
dragonfly/accessibility/utils.py
dragonfly/actions/__init__.py
dragonfly/actions/_generate_typeables.py
dragonfly/actions/_test_playsound.py
dragonfly/actions/_test_startapp.py
dragonfly/actions/_test_x11_text_key.py
dragonfly/actions/action_base.py
dragonfly/actions/action_base_keyboard.py
dragonfly/actions/action_cmd.py
dragonfly/actions/action_context.py
dragonfly/actions/action_focuswindow.py
dragonfly/actions/action_function.py
dragonfly/actions/action_key.py
dragonfly/actions/action_mimic.py
dragonfly/actions/action_mouse.py
dragonfly/actions/action_paste.py
dragonfly/actions/action_pause.py
dragonfly/actions/action_playback.py
dragonfly/actions/action_playsound.py
dragonfly/actions/action_startapp.py
dragonfly/actions/action_text.py
dragonfly/actions/action_waitwindow.py
dragonfly/actions/actions.py
dragonfly/actions/natlinkinput.py
dragonfly/actions/sendinput.py
dragonfly/actions/typeables.py
dragonfly/actions/keyboard/__init__.py
dragonfly/actions/keyboard/_base.py
dragonfly/actions/keyboard/_pynput.py
dragonfly/actions/keyboard/_win32.py
dragonfly/actions/keyboard/_x11_base.py
dragonfly/actions/keyboard/_x11_libxdo.py
dragonfly/actions/keyboard/_x11_xdotool.py
dragonfly/actions/mouse/__init__.py
dragonfly/actions/mouse/_base.py
dragonfly/actions/mouse/_pynput.py
dragonfly/actions/mouse/_win32.py
dragonfly/actions/mouse/_xdotool.py
dragonfly/engines/__init__.py
dragonfly/engines/backend_kaldi/__init__.py
dragonfly/engines/backend_kaldi/audio.py
dragonfly/engines/backend_kaldi/compiler.py
dragonfly/engines/backend_kaldi/dictation.py
dragonfly/engines/backend_kaldi/engine.py
dragonfly-1.0.0rc2.dist-info/AUTHORS.txt
dragonfly-1.0.0rc2.dist-info/LICENSE.txt
dragonfly-1.0.0rc2.dist-info/METADATA
dragonfly-1.0.0rc2.dist-info/WHEEL
dragonfly-1.0.0rc2.dist-info/top_level.txt
dragonfly-1.0.0rc2.dist-info/RECORD
