Metadata-Version: 2.1
Name: dragonfly
Version: 1.0.0rc2
Summary: Speech recognition extension library
Home-page: https://github.com/dictation-toolbox/dragonfly
Author: Christo Butcher
Author-email: dist.dragonfly@twizzy.biz
Maintainer: Dane Finlay
Maintainer-email: dane@danefinlay.net
License: LICENSE.txt
Platform: UNKNOWN
Classifier: Development Status :: 5 - Production/Stable
Classifier: Environment :: Win32 (MS Windows)
Classifier: Environment :: X11 Applications
Classifier: Environment :: MacOS X
Classifier: License :: OSI Approved :: GNU Library or Lesser General Public License (LGPL)
Classifier: Intended Audience :: Developers
Classifier: Operating System :: Microsoft :: Windows
Classifier: Operating System :: POSIX
Classifier: Operating System :: MacOS
Classifier: Programming Language :: Python :: 2.7
Classifier: Programming Language :: Python :: 3.4
Classifier: Programming Language :: Python :: 3.5
Classifier: Programming Language :: Python :: 3.6
Classifier: Programming Language :: Python :: 3.7
Classifier: Programming Language :: Python :: 3.8
Classifier: Programming Language :: Python :: 3.9
Classifier: Programming Language :: Python :: 3.10
Classifier: Programming Language :: Python :: Implementation :: CPython
Classifier: Topic :: Multimedia :: Sound/Audio :: Speech
Classifier: Topic :: Software Development :: Libraries :: Python Modules
Requires-Dist: setuptools (>=40.0.0)
Requires-Dist: packaging (>=19.0)
Requires-Dist: six
Requires-Dist: lark-parser (==0.8.*)
Requires-Dist: psutil (>=5.5.1) ; os_name == "posix"
Requires-Dist: pyperclip (>=1.7.0) ; os_name == "posix"
Requires-Dist: pynput (>=1.7.6) ; os_name == "posix"
Requires-Dist: pyobjc (>=5.2) ; platform_system == "Darwin"
Requires-Dist: py-applescript (==1.0.0) ; platform_system == "Darwin"
Requires-Dist: pywin32 ; platform_system == "Windows"
Provides-Extra: accessibility
Requires-Dist: comtypes ; (platform_system == "Windows") and extra == 'accessibility'
Requires-Dist: enum34 ; (python_version < "3.4") and extra == 'accessibility'
Requires-Dist: regex (<2022.1.18) ; (python_version <= "2.7") and extra == 'accessibility'
Requires-Dist: regex ; (python_version > "2.7") and extra == 'accessibility'
Provides-Extra: kaldi
Requires-Dist: kaldi-active-grammar (~=3.1.0) ; extra == 'kaldi'
Requires-Dist: sounddevice (==0.3.*) ; extra == 'kaldi'
Requires-Dist: webrtcvad-wheels (==2.0.*) ; extra == 'kaldi'
Provides-Extra: playsound
Requires-Dist: sounddevice (==0.3.*) ; (os_name == "posix") and extra == 'playsound'
Provides-Extra: sphinx
Requires-Dist: sounddevice (==0.3.*) ; extra == 'sphinx'
Requires-Dist: sphinxwrapper (>=1.3.0) ; extra == 'sphinx'
Requires-Dist: pyjsgf (==1.9.*) ; extra == 'sphinx'
Provides-Extra: test
Requires-Dist: pytest (==3.9.*) ; extra == 'test'
